{
  "FRI": [
    [
      {
        "origin": "CONC",
        "line": "01",
        "destination": "MCAR"
      },
      {
        "origin": "MCAR",
        "line": "04",
        "destination": "BAYF"
      },
      {
        "origin": "BAYF",
        "line": "12",
        "destination": "CAST"
      }
    ]
  ],
  "SAT": [
    [
      {
        "origin": "CONC",
        "line": "01",
        "destination": "MCAR"
      },
      {
        "origin": "MCAR",
        "line": "04",
        "destination": "BAYF"
      },
      {
        "origin": "BAYF",
        "line": "12",
        "destination": "CAST"
      }
    ]
  ],
  "SUN": [
    [
      {
        "origin": "CONC",
        "line": "01",
        "destination": "MCAR"
      },
      {
        "origin": "MCAR",
        "line": "04",
        "destination": "BAYF"
      },
      {
        "origin": "BAYF",
        "line": "12",
        "destination": "CAST"
      }
    ]
  ]
}
