{
  "FRI": [
    [
      {
        "origin": "EMBR",
        "line": "06",
        "destination": "SHAY"
      }
    ],
    [
      {
        "origin": "EMBR",
        "line": "12",
        "destination": "BAYF"
      },
      {
        "origin": "BAYF",
        "line": "04",
        "destination": "SHAY"
      }
    ]
  ],
  "SAT": [
    [
      {
        "origin": "EMBR",
        "line": "06",
        "destination": "SHAY"
      }
    ],
    [
      {
        "origin": "EMBR",
        "line": "12",
        "destination": "BAYF"
      },
      {
        "origin": "BAYF",
        "line": "04",
        "destination": "SHAY"
      }
    ]
  ],
  "SUN": [
    [
      {
        "origin": "EMBR",
        "line": "12",
        "destination": "BAYF"
      },
      {
        "origin": "BAYF",
        "line": "04",
        "destination": "SHAY"
      }
    ]
  ]
}
