{
  "FRI": [
    [
      {
        "origin": "HAYW",
        "line": "05",
        "destination": "BALB"
      },
      {
        "origin": "BALB",
        "line": "01",
        "destination": "SFIA"
      }
    ],
    [
      {
        "origin": "HAYW",
        "line": "03",
        "destination": "BAYF"
      },
      {
        "origin": "BAYF",
        "line": "11",
        "destination": "BALB"
      },
      {
        "origin": "BALB",
        "line": "01",
        "destination": "SFIA"
      }
    ]
  ],
  "SAT": [
    [
      {
        "origin": "HAYW",
        "line": "05",
        "destination": "BALB"
      },
      {
        "origin": "BALB",
        "line": "01",
        "destination": "SFIA"
      }
    ],
    [
      {
        "origin": "HAYW",
        "line": "03",
        "destination": "BAYF"
      },
      {
        "origin": "BAYF",
        "line": "11",
        "destination": "BALB"
      },
      {
        "origin": "BALB",
        "line": "01",
        "destination": "SFIA"
      }
    ]
  ],
  "SUN": [
    [
      {
        "origin": "HAYW",
        "line": "03",
        "destination": "BAYF"
      },
      {
        "origin": "BAYF",
        "line": "11",
        "destination": "BALB"
      },
      {
        "origin": "BALB",
        "line": "01",
        "destination": "SFIA"
      }
    ]
  ]
}
