{
  "FRI": [
    [
      {
        "origin": "LAKE",
        "line": "11",
        "destination": "DALY"
      }
    ],
    [
      {
        "origin": "LAKE",
        "line": "05",
        "destination": "DALY"
      }
    ]
  ],
  "SAT": [
    [
      {
        "origin": "LAKE",
        "line": "05",
        "destination": "DALY"
      }
    ],
    [
      {
        "origin": "LAKE",
        "line": "11",
        "destination": "DALY"
      }
    ]
  ],
  "SUN": [
    [
      {
        "origin": "LAKE",
        "line": "11",
        "destination": "DALY"
      }
    ]
  ]
}
