{
  "FRI": [
    [
      {
        "origin": "RICH",
        "line": "04",
        "destination": "MCAR"
      }
    ],
    [
      {
        "origin": "RICH",
        "line": "07",
        "destination": "MCAR"
      }
    ]
  ],
  "SAT": [
    [
      {
        "origin": "RICH",
        "line": "07",
        "destination": "MCAR"
      }
    ],
    [
      {
        "origin": "RICH",
        "line": "04",
        "destination": "MCAR"
      }
    ]
  ],
  "SUN": [
    [
      {
        "origin": "RICH",
        "line": "04",
        "destination": "MCAR"
      }
    ]
  ]
}
