{
  "FRI": [
    [
      {
        "origin": "SFIA",
        "line": "02",
        "destination": "BALB"
      },
      {
        "origin": "BALB",
        "line": "06",
        "destination": "UCTY"
      }
    ],
    [
      {
        "origin": "SFIA",
        "line": "02",
        "destination": "BALB"
      },
      {
        "origin": "BALB",
        "line": "12",
        "destination": "BAYF"
      },
      {
        "origin": "BAYF",
        "line": "04",
        "destination": "UCTY"
      }
    ]
  ],
  "SAT": [
    [
      {
        "origin": "SFIA",
        "line": "02",
        "destination": "BALB"
      },
      {
        "origin": "BALB",
        "line": "12",
        "destination": "BAYF"
      },
      {
        "origin": "BAYF",
        "line": "04",
        "destination": "UCTY"
      }
    ]
  ],
  "SUN": [
    [
      {
        "origin": "SFIA",
        "line": "02",
        "destination": "BALB"
      },
      {
        "origin": "BALB",
        "line": "12",
        "destination": "BAYF"
      },
      {
        "origin": "BAYF",
        "line": "04",
        "destination": "UCTY"
      }
    ]
  ]
}
