{
  "FRI": [
    [
      {
        "origin": "UCTY",
        "line": "05",
        "destination": "MONT"
      }
    ],
    [
      {
        "origin": "UCTY",
        "line": "03",
        "destination": "BAYF"
      },
      {
        "origin": "BAYF",
        "line": "11",
        "destination": "MONT"
      }
    ]
  ],
  "SAT": [
    [
      {
        "origin": "UCTY",
        "line": "05",
        "destination": "MONT"
      }
    ],
    [
      {
        "origin": "UCTY",
        "line": "03",
        "destination": "BAYF"
      },
      {
        "origin": "BAYF",
        "line": "11",
        "destination": "MONT"
      }
    ]
  ],
  "SUN": [
    [
      {
        "origin": "UCTY",
        "line": "03",
        "destination": "BAYF"
      },
      {
        "origin": "BAYF",
        "line": "11",
        "destination": "MONT"
      }
    ]
  ]
}
