{
  "FRI": [
    [
      {
        "origin": "WOAK",
        "line": "01",
        "destination": "POWL"
      }
    ],
    [
      {
        "origin": "WOAK",
        "line": "11",
        "destination": "POWL"
      }
    ],
    [
      {
        "origin": "WOAK",
        "line": "07",
        "destination": "POWL"
      }
    ],
    [
      {
        "origin": "WOAK",
        "line": "05",
        "destination": "POWL"
      }
    ]
  ],
  "SAT": [
    [
      {
        "origin": "WOAK",
        "line": "01",
        "destination": "POWL"
      }
    ],
    [
      {
        "origin": "WOAK",
        "line": "05",
        "destination": "POWL"
      }
    ],
    [
      {
        "origin": "WOAK",
        "line": "07",
        "destination": "POWL"
      }
    ],
    [
      {
        "origin": "WOAK",
        "line": "11",
        "destination": "POWL"
      }
    ]
  ],
  "SUN": [
    [
      {
        "origin": "WOAK",
        "line": "01",
        "destination": "POWL"
      }
    ],
    [
      {
        "origin": "WOAK",
        "line": "11",
        "destination": "POWL"
      }
    ]
  ]
}
